<?xml version="1.0" encoding="utf-8" ?>
<Defs>
    <PawnKindDef ParentName="THU_XenomorphBase">
        <defName>THU_Facehugger</defName>
        <label>Facehugger</label>
        <race>THU_Facehugger</race>
        <combatPower>33</combatPower>
        <aiAvoidCover>true</aiAvoidCover>
        <lifeStages>
            <li>
                <bodyGraphicData>
                    <texPath>THU_Facehugger</texPath>
                    <graphicClass>Graphic_Multi</graphicClass>
                    <drawSize>1</drawSize>
                    <shadowData>
                        <volume>(0.7, 0.6, 0.4)</volume>
                        <offset>(0,0,-0.25)</offset>
                    </shadowData>
                </bodyGraphicData>
                <dessicatedBodyGraphicData>
                    <texPath>Things/Pawn/Animal/Dessicated/CritterDessicatedSmall</texPath>
                    <drawSize>1</drawSize>
                </dessicatedBodyGraphicData>
            </li>
        </lifeStages>
    </PawnKindDef>
</Defs>
